tkkillablethreads/README.MD
tkkillablethreads/__init__.py
tkkillablethreads/requirements.txt
tkkillablethreads/thirdparty.json
tkkillablethreads-0.10.dist-info/LICENSE.rst
tkkillablethreads-0.10.dist-info/METADATA
tkkillablethreads-0.10.dist-info/WHEEL
tkkillablethreads-0.10.dist-info/top_level.txt
tkkillablethreads-0.10.dist-info/RECORD
