Metadata-Version: 2.1
Name: tkkillablethreads
Version: 0.10
Summary: Killable, non-blocking threads for tkinter
Home-page: https://github.com/hansalemaos/tkkillablethreads
Author: Johannes Fischer
Author-email: aulasparticularesdealemaosp@gmail.com
License: MIT
Keywords: tkinter,threads
Classifier: Development Status :: 4 - Beta
Classifier: Programming Language :: Python :: 3 :: Only
Classifier: Programming Language :: Python :: 3.10
Classifier: Topic :: Software Development :: Libraries :: Python Modules
Classifier: Topic :: Utilities
License-File: LICENSE.rst
